nanoparticleatomcounting/__init__.py
nanoparticleatomcounting/atom_count.py
nanoparticleatomcounting/by_area.py
nanoparticleatomcounting/by_volume.py
nanoparticleatomcounting/count_utilities.py
nanoparticleatomcounting/data.py
nanoparticleatomcounting-0.1.1.dist-info/licenses/LICENSE
nanoparticleatomcounting-0.1.1.dist-info/METADATA
nanoparticleatomcounting-0.1.1.dist-info/WHEEL
nanoparticleatomcounting-0.1.1.dist-info/entry_points.txt
nanoparticleatomcounting-0.1.1.dist-info/top_level.txt
nanoparticleatomcounting-0.1.1.dist-info/RECORD
