Metadata-Version: 2.4
Name: nanoparticleatomcounting
Version: 0.1.1
Summary: Estimate atom counts in metal nanoparticles given radius and contact angle
Home-page: https://github.com/giolajide/nanoparticleatomcounting
Author: Gbolagade Olajide
Author-email: giolajide@crimson.ua.edu
License: MIT
Project-URL: Bug Tracker, https://github.com/giolajide/nanoparticleatomcounting/issues
Project-URL: Documentation, https://github.com/giolajide/nanoparticleatomcounting#readme
Keywords: nanoparticle,tem,electron microscopy,active site
Classifier: Development Status :: 3 - Alpha
Classifier: Intended Audience :: Science/Research
Classifier: Topic :: Scientific/Engineering :: Chemistry
Classifier: License :: OSI Approved :: MIT License
Classifier: Programming Language :: Python :: 3
Classifier: Programming Language :: Python :: 3.8
Classifier: Programming Language :: Python :: 3.9
Classifier: Programming Language :: Python :: 3.10
Requires-Python: >=3.8
License-File: LICENSE
Requires-Dist: numpy<2.3,>=1.20
Requires-Dist: pandas>=1.4
Requires-Dist: streamlit<2.0,>=1.4
Requires-Dist: openpyxl>=3.1.0
Requires-Dist: xlrd>=2.0.1
Dynamic: author
Dynamic: author-email
Dynamic: classifier
Dynamic: description
Dynamic: description-content-type
Dynamic: home-page
Dynamic: keywords
Dynamic: license
Dynamic: license-file
Dynamic: project-url
Dynamic: requires-dist
Dynamic: requires-python
Dynamic: summary
